aido/__init__.py
aido/agents/__init__.py
aido/agents/agent_base.py
aido/agents/agent_func.py
aido/agents/api.py
aido/agents/llm_settings.py
aido/agents/metadata.py
aido/agents/oauth.py
aido/llms/__init__.py
aido/memory/__init__.py
aido/registry/__init__.py
aido/router/__init__.py
aido/utils/__init__.py
aido/web_ui/__init__.py
aido-0.1.0.dist-info/METADATA
aido-0.1.0.dist-info/WHEEL
aido-0.1.0.dist-info/RECORD
