Metadata-Version: 2.1
Name: aido
Version: 0.1.0
Summary: 
Author: ericjiang
Author-email: aido.ai@outlook.com
Requires-Python: >=3.10,<4.0
Classifier: Programming Language :: Python :: 3
Classifier: Programming Language :: Python :: 3.10
Classifier: Programming Language :: Python :: 3.11
Requires-Dist: pydantic
Requires-Dist: requests (>=2.28.1,<3.0.0)
